warp/__init__.py
warp/bibtex.py
warp/constants.py
warp/protocols.conf
warp/utils.py
warp/warp_logo.png
warp/wizards.py
warp/protocols/__init__.py
warp/protocols/protocol_base.py
warp/protocols/protocol_deconv_mics.py
warp/protocols/protocol_deconv_tomo.py
warp/protocols/protocol_deconv_ts.py
warp/protocols/protocol_m_high_resolution_refinements.py
warp/protocols/protocol_motion_ctf.py
warp/protocols/protocol_tomoReconstruct.py
warp/protocols/protocol_tomo_export_particles.py
warp/protocols/protocol_ts_motion_ctf.py
warp/protocols/protocol_ts_template_match.py
warp/tests/__init__.py
warp/tests/protocols_tomo_tests.py
warp/tests/test_protocols.py
warp/tests/test_tomo.py
scipion_em_warp-3.6.2.dist-info/LICENSE
scipion_em_warp-3.6.2.dist-info/METADATA
scipion_em_warp-3.6.2.dist-info/WHEEL
scipion_em_warp-3.6.2.dist-info/entry_points.txt
scipion_em_warp-3.6.2.dist-info/top_level.txt
scipion_em_warp-3.6.2.dist-info/RECORD
