Metadata-Version: 2.1
Name: scipion-em-warp
Version: 3.6.2
Summary: Plugin to use Warp within the Scipion framework
Author-email: Grigory Sharov <sharov.grigory@gmail.com>, Yunior Fonseca <cfonseca@cnb.csic.es>, Pablo Conesa <pconesa@cnb.csic.es>
License: GNU General Public License v3 (GPLv3)
Project-URL: Homepage, https://github.com/scipion-em/scipion-em-warp
Project-URL: Repository, https://github.com/scipion-em/scipion-em-warp
Project-URL: Issues, https://github.com/scipion-em/scipion-em-warp/issues
Keywords: scipion,electron-microscopy,cryo-em,structural-biology,image-processing,scipion-3.0
Requires-Python: >=3.8
License-File: LICENSE
Requires-Dist: scipion-em>=3.9.3
Requires-Dist: scipion-pyworkflow>=3.10.6
Requires-Dist: scipion-em-reliontomo>=4.0.2
